haptic_master/__init__.py
haptic_master/base.py
haptic_master/effect.py
haptic_master/haptic_master.py
haptic_master/object.py
haptic_master-0.1.3.dist-info/LICENSE
haptic_master-0.1.3.dist-info/METADATA
haptic_master-0.1.3.dist-info/WHEEL
haptic_master-0.1.3.dist-info/top_level.txt
haptic_master-0.1.3.dist-info/RECORD
