Metadata-Version: 2.1
Name: haptic-master
Version: 0.1.3
Summary: A package for controlling the HapticMaster robot using TCP/IP
Author-email: Ozan Tokatli <ozan.tokatli@gmail.com>
Project-URL: Homepage, https://github.com/otokatli/pyHapticMaster
Project-URL: Documentation, https://pyhapticmaster.readthedocs.io/
Classifier: Programming Language :: Python :: 3
Classifier: License :: OSI Approved :: MIT License
Classifier: Operating System :: OS Independent
Classifier: Development Status :: 3 - Alpha
Classifier: Intended Audience :: Science/Research
Requires-Python: >=3.10
License-File: LICENSE
